{
  "showId": "sister-act-2011",
  "outletId": "bloomberg-news",
  "outlet": "Bloomberg News",
  "criticName": "Jeremy Gerard",
  "url": "http://www.bloomberg.com/news/2011-04-21/whoopi-goldberg-s-swinging-nuns-rock-rousing-sister-act-jeremy-gerard.html",
  "source": "bww-reviews",
  "sources": [
    "bww-reviews",
    "bww-roundup"
  ],
  "bwwExcerpt": "Nothing unexpected happens in “Sister Act,” a fairy tale we already know. But it’s delivered with exceptional glee and polish.",
  "bwwScore": 8,
  "contentTier": "excerpt",
  "bwwRoundupUrl": "https://www.broadwayworld.com/article/Broadway-Review-Roundup-SISTER-ACT-Updating-LIVE-20110420"
}
