{
  "showId": "a-steady-rain-2009",
  "outletId": "usatoday",
  "outlet": "USA Today",
  "criticName": "Elysa Gardner",
  "url": "http://www.usatoday.com/life/theater/reviews/2009-09-29-steady-rain-jackman-craig_N.htm?csp=34",
  "source": "bww-roundup",
  "sources": [
    "bww-roundup"
  ],
  "bwwExcerpt": "\"The events informing A Steady Rain (* * *½ out of four) would make a heck of an action movie. And the cast of Keith Huff's new drama, which opened Tuesday at Broadway's Gerald Schoenfeld Theatre, consists of two superstars who have ample experience in that arena ... Huff's briskly absorbing script has its clichés and contrivances, but Denny and Joey are drawn with such earthy wit and non-patronizing compassion that Rain never rings false or superficial. It's hard to im",
  "bwwRoundupUrl": "https://www.broadwayworld.com/article/Broadway-Blog-Review-Roundup-A-STEADY-RAIN-20090929",
  "contentTier": "excerpt"
}
