{
  "showId": "the-new-one-2018",
  "outletId": "vulture",
  "outlet": "Vulture",
  "criticName": "David Fox",
  "url": null,
  "publishDate": null,
  "fullText": null,
  "isFullReview": false,
  "bwwExcerpt": "J.D.F.: A little bit of both! But, yes, I did like it. The comedy was super-strong. Lots of different types of jokes, expertly crafted. I probably say this after all of his shows, but it's the funniest one yet. More than anything, though, I was most impressed by how it's structured. S.H.: Honestly, ...",
  "bwwRoundupUrl": null,
  "bwwThumb": null,
  "showScoreExcerpt": null,
  "contentTier": "excerpt",
  "contentTierReason": "Only aggregator excerpts available",
  "source": "bww-roundup",
  "sources": [
    "bww-roundup"
  ]
}
