{
  "showId": "hughie-2016",
  "outletId": "thewrap",
  "outlet": "TheWrap",
  "criticName": "Robert Hofler",
  "url": null,
  "publishDate": null,
  "fullText": null,
  "isFullReview": false,
  "bwwExcerpt": "In between Erie's many monologues, Grandage interjects speechless longueurs in which the actor either sits or stands around with nothing to do as shades of green sweep over him like waves of smog...On stage, Whitaker's voice is much higher pitched than in the movies...Whitaker uses that contrast in ...",
  "bwwRoundupUrl": null,
  "bwwThumb": null,
  "showScoreExcerpt": null,
  "contentTier": "excerpt",
  "contentTierReason": "Only aggregator excerpts available",
  "source": "bww-roundup",
  "sources": [
    "bww-roundup"
  ]
}
