{
  "showId": "the-color-purple-2005",
  "outletId": "curtainup",
  "outlet": "CurtainUp",
  "criticName": "Simon Saltzman",
  "url": "http://www.curtainup.com/colorpurple15.html",
  "publishDate": null,
  "fullText": null,
  "isFullReview": false,
  "dtliExcerpt": null,
  "originalScore": null,
  "assignedScore": null,
  "source": "show-score-playwright",
  "dtliThumb": null,
  "dtliUrl": null,
  "bwwExcerpt": null,
  "bwwRoundupUrl": null,
  "showScoreExcerpt": "\"'The Color Purple' is a rewarding show thanks to some powerful performances…The book that Marsha Norman has written for this musical version is admirably terse but far from frail…This production will certainly please those who enjoy the City Center Encore series of staged musical revivals, while others may feel a little cheated by its economy of production values. At its best, Doyle's artistic choices never compromise Marsh Norman's tough and tender book.\"\n\nRead more",
  "contentTier": "excerpt",
  "contentTierReason": "Only aggregator excerpts available",
  "sources": [
    "show-score-playwright"
  ]
}