{
  "showId": "a-view-from-the-bridge-2010",
  "outletId": "variety",
  "outlet": "Variety",
  "criticName": "Charles Isherwood",
  "url": "https://variety.com/2010/legit/reviews/a-view-from-the-bridge-1117941773/",
  "publishDate": "January 24, 2010",
  "fullText": null,
  "isFullReview": false,
  "dtliExcerpt": "Liev Schreiber brings a burning intensity to the role of Eddie Carbone in this muscular revival of Arthur Miller's 1955 drama, directed with sure hands by Gregory Mosher.",
  "originalScore": null,
  "assignedScore": null,
  "source": "web-search",
  "dtliThumb": null,
  "dtliUrl": null,
  "bwwExcerpt": null,
  "bwwRoundupUrl": null,
  "showScoreExcerpt": "Liev Schreiber brings a burning intensity to the role of Eddie Carbone in this muscular revival of Arthur Miller's 1955 drama, directed with sure hands by Gregory Mosher.",
  "contentTier": "excerpt",
  "contentTierReason": "Only aggregator excerpts available"
}