{
  "showId": "the-ferryman-2018",
  "outletId": "valleyadvocate",
  "outlet": "valleyadvocate",
  "criticName": "Chris Rohmann",
  "url": "https://valleyadvocate.com/2019/02/15/stagestruck-big-apple-bites/",
  "publishDate": null,
  "fullText": null,
  "isFullReview": false,
  "dtliExcerpt": null,
  "originalScore": null,
  "assignedScore": null,
  "source": "show-score-playwright",
  "dtliThumb": null,
  "dtliUrl": null,
  "bwwExcerpt": null,
  "bwwRoundupUrl": null,
  "showScoreExcerpt": "“’The Ferryman’ explodes in sudden disclosures, confessions, and reprisals – a bit too much at once. But that’s a quibble with one of the richest theatrical experiences I can remember...Almost every minute of Butterworth’s three-hours-plus epic is bursting with energy, passion and yes, humor and heart aplenty...This season’s must-see Broadway hit...The cast, across-the-board-fabulous.”\n\nRead more",
  "contentTier": "excerpt",
  "contentTierReason": "Only aggregator excerpts available",
  "sources": [
    "show-score-playwright"
  ]
}