{
  "showId": "the-picture-of-dorian-gray-2025",
  "outletId": "theatre-reviews-limited",
  "outlet": "Theatre Reviews Limited",
  "criticName": "Joseph Verlezza",
  "url": "https://www.theatrereviews.com/broadway-review-the-picture-of-dorian-gray-at-the-music-box-theatre-through-sunday-june-15-2025/",
  "publishDate": null,
  "fullText": null,
  "isFullReview": false,
  "dtliExcerpt": null,
  "originalScore": null,
  "assignedScore": null,
  "source": "show-score-playwright",
  "dtliThumb": null,
  "dtliUrl": null,
  "bwwExcerpt": null,
  "bwwRoundupUrl": null,
  "showScoreExcerpt": "Ms Snook is masterful as she navigates through the hyperactive and interactive proceedings\n\nRead more",
  "contentTier": "excerpt",
  "contentTierReason": "Only aggregator excerpts available"
}