{
  "showId": "merrily-we-roll-along-2023",
  "outletId": "theatermania",
  "outlet": "TheaterMania",
  "criticName": "David Gordon",
  "url": "https://www.theatermania.com/news/review-its-a-hit-daniel-radcliffe-jonathan-groff-and-lindsay-mendez-bring-heavenly-merrily-we-roll-along-to-broadway_1717001/",
  "publishDate": "October 10, 2023",
  "fullText": "Sitting comfortably in the Hudson Theatre, this Merrily is one of those transcendent productions I’ll look back on fondly forever.",
  "originalScore": null,
  "assignedScore": null,
  "dtliThumb": "Up",
  "source": "dtli"
}