{
  "showId": "hello-dolly-2017",
  "outletId": "out-magazine",
  "outlet": "out-magazine",
  "criticName": "Michael Musto",
  "url": "http://www.out.com/michael-musto/2017/4/24/bianca-del-rio-id-let-trump-touch-my-psy",
  "publishDate": null,
  "fullText": null,
  "isFullReview": false,
  "dtliExcerpt": null,
  "originalScore": null,
  "assignedScore": null,
  "source": "show-score-playwright",
  "dtliThumb": null,
  "dtliUrl": null,
  "bwwExcerpt": null,
  "bwwRoundupUrl": null,
  "showScoreExcerpt": "\"Pure entertainment of the most delicious kind. With peppy choreography by Warren Carlyle and candy-colored sets and costumes courtesy of Santo Loquasto, the show is an eyeful, and with performers like Gavin Creel and Kate Baldwin aboard, it’s an earful too...Bette has long been a master at deftly intertwining sassy and sweet...Throughout, Bette seems to be having a high time, even adding some of her personal vocal phrasings, along with quirky pronunciations.\"\n\nRead more",
  "contentTier": "excerpt",
  "contentTierReason": "Only aggregator excerpts available"
}