{
  "showId": "king-charles-iii-2015",
  "outletId": "the-three-tomatoes",
  "outlet": "The Three Tomatoes",
  "criticName": "Valerie Samaldone",
  "url": "http://thethreetomatoes.com/new-on-broadway-king-charles-ii-and-therese-raquin",
  "publishDate": null,
  "fullText": null,
  "isFullReview": false,
  "dtliExcerpt": null,
  "originalScore": null,
  "assignedScore": null,
  "source": "show-score-playwright",
  "dtliThumb": null,
  "dtliUrl": null,
  "bwwExcerpt": null,
  "bwwRoundupUrl": null,
  "showScoreExcerpt": "\"'King Charles III' is a clever piece of British theatre which clearly could delight anyone obsessed with stories about British royalty...Now, this piece is a full 2 hours and 30 minutes. I believe it could have been really great if a good 40 minutes were cut out. Seriously...There was just too much talking and dialogue that felt tedious, at best...It’s not that I don’t have the attention span, it’s just that some of these plays simply don’t warrant the overwriting. Clever, funny, too long.\"\n\nRead more",
  "contentTier": "excerpt",
  "contentTierReason": "Only aggregator excerpts available"
}