{
  "showId": "summer-1976-2023",
  "outletId": "theater-life",
  "outlet": "Theater Life",
  "criticName": "Samuel L. Leiter",
  "url": "https://theaterlife.com/summer-1976/",
  "publishDate": null,
  "fullText": null,
  "isFullReview": false,
  "dtliExcerpt": null,
  "originalScore": null,
  "assignedScore": null,
  "source": "show-score-playwright",
  "dtliThumb": null,
  "dtliUrl": null,
  "bwwExcerpt": null,
  "bwwRoundupUrl": null,
  "showScoreExcerpt": "“The play is a sweet time-passer of no particular theatrical importance, delightfully acted, directed, and designed, with moments of laughter and pathos coated in a light glaze of nostalgia.”\n\nRead more",
  "contentTier": "excerpt",
  "contentTierReason": "Only aggregator excerpts available"
}