{
  "showId": "the-terms-of-my-surrender-2017",
  "outletId": "frontmezzjunkies",
  "outlet": "Front Mezz Junkies",
  "criticName": "Steven Ross",
  "url": "https://frontmezzjunkies.com/2017/08/18/the-terms-of-my-surrender/",
  "publishDate": null,
  "fullText": null,
  "isFullReview": false,
  "dtliExcerpt": null,
  "originalScore": null,
  "assignedScore": null,
  "source": "show-score-playwright",
  "dtliThumb": null,
  "dtliUrl": null,
  "bwwExcerpt": null,
  "bwwRoundupUrl": null,
  "showScoreExcerpt": "\"The show is surprisingly humorous and filled with stories that are meant to inspire and inform...There are many moments that border on the self-congratulatory, but also feel important and inspirational. Others feel like old late-night talk-show skits that have lost their political zing...Moore is preaching to a New York like-minded liberal choir, and begging us, in essence, to stand up and do something, no matter how small or insignificant it feels at the time.\"\n\nRead more",
  "contentTier": "excerpt",
  "contentTierReason": "Only aggregator excerpts available"
}