{
  "showId": "the-other-place-2013",
  "outletId": "artsdesk",
  "outlet": "The Arts Desk",
  "criticName": "Demetrios Matheou",
  "url": "https://theartsdesk.com/theatre/other-place-national-theatre-review-searing-family-tragedy",
  "publishDate": null,
  "fullText": null,
  "isFullReview": false,
  "dtliExcerpt": null,
  "originalScore": null,
  "assignedScore": null,
  "source": "show-score-playwright",
  "dtliThumb": null,
  "dtliUrl": null,
  "bwwExcerpt": null,
  "bwwRoundupUrl": null,
  "showScoreExcerpt": "\"Zeldin has conjured a novel tragedy that...feels horribly of the here and now.\"\n\nRead more",
  "contentTier": "excerpt",
  "contentTierReason": "Only aggregator excerpts available"
}