{
  "showId": "the-inheritance-2019",
  "outletId": "theatermania",
  "outlet": "TheaterMania",
  "criticName": "Zachary Stewart",
  "url": "https://www.theatermania.com/broadway/reviews/the-inheritance-broadway-gay-men-matthew-lopez_90178.html",
  "publishDate": null,
  "fullText": null,
  "isFullReview": false,
  "dtliExcerpt": null,
  "originalScore": null,
  "assignedScore": null,
  "source": "show-score-playwright",
  "dtliThumb": null,
  "dtliUrl": null,
  "bwwExcerpt": null,
  "bwwRoundupUrl": null,
  "showScoreExcerpt": "\"'The Inheritance' on Broadway Appraises the Legacy of Gay Life in America: Matthew Lopez's stunning new play comes home to New York after an award-winning run in London.\"\n\nRead more",
  "contentTier": "excerpt",
  "contentTierReason": "Only aggregator excerpts available"
}