{
  "showId": "the-velocity-of-autumn-2014",
  "outletId": "timeout",
  "outlet": "Time Out New York",
  "criticName": "David Cote",
  "url": "http://www.timeout.com/newyork/theater/the-velocity-of-autumn",
  "publishDate": null,
  "fullText": null,
  "isFullReview": false,
  "bwwExcerpt": "Ironically, the dominant sensation produced by Eric Coble's anemic two-hander is also that of growing old. The minutes slip by, you lose feeling in parts of your body and find yourself 90 minutes closer to the grave, with nothing to show for it but a crumpled Playbill....",
  "bwwRoundupUrl": null,
  "bwwThumb": null,
  "showScoreExcerpt": null,
  "contentTier": "excerpt",
  "contentTierReason": "Only aggregator excerpts available",
  "source": "bww-roundup",
  "sources": [
    "bww-roundup",
    "playbill-verdict"
  ],
  "playbillVerdictUrl": "http://www.timeout.com/newyork/theater/the-velocity-of-autumn",
  "duplicateOf": "timeout--unknown.json"
}
