{
  "showId": "good-night-and-good-luck-2025",
  "outletId": "deadline",
  "outlet": "Deadline",
  "criticName": "Greg Evans",
  "url": "https://deadline.com/2025/04/good-night-and-good-luck-broadway-review-george-clooney-1236357126/",
  "playbillVerdictUrl": "https://deadline.com/2025/04/good-night-and-good-luck-broadway-review-george-clooney-1236357126/",
  "source": "playbill-verdict",
  "sources": [
    "playbill-verdict",
    "bww-roundup"
  ],
  "bwwExcerpt": "Good Night, and Good Luck certainly doesn’t lack point of view or conviction, but neither of those things can do much with an overly familiar story, a lack of subtlety and an odd tone of understatement that extends to everything from the writing to Clooney’s performance.",
  "bwwRoundupUrl": "https://www.broadwayworld.com/article/Review-Roundup-GOOD-NIGHT-AND-GOOD-LUCK-Brings-George-Clooney-To-Broadway-20250403"
}
