{
  "showId": "prayer-for-the-french-republic-2024",
  "outletId": "theatermania",
  "outlet": "TheaterMania",
  "criticName": "Zachary Stewart",
  "url": "https://www.theatermania.com/news/review-prayer-for-the-french-republic-and-a-one-way-ticket-to-israel_1725360/",
  "publishDate": "January 9, 2024",
  "fullText": "In three acts, Harmon brilliantly dramatizes these questions and more through the story of one very specific yet completely recognizable Jewish family (fans of last season’s Leopoldstadt will find much to admire here). Scenes of simmering resentment imperceptibly come to a boil as family politics brush up against seismic global forces.",
  "originalScore": null,
  "assignedScore": null,
  "dtliThumb": "Up",
  "source": "dtli"
}