{
  "showId": "motown-the-musical-2016",
  "outletId": "village-voice",
  "outlet": "The Village Voice",
  "criticName": "Unknown",
  "url": "http://blogs.villagevoice.com/dailymusto/2013/04/motown_the_musi_2.php",
  "playbillVerdictUrl": "http://blogs.villagevoice.com/dailymusto/2013/04/motown_the_musi_2.php",
  "source": "playbill-verdict",
  "sources": [
    "playbill-verdict"
  ],
  "wrongProduction": true,
  "wrongProductionReason": "URL/date from 2013 but show opened 2016 (year gap: 3)"
}
