{
  "showId": "the-rocky-horror-show-2026",
  "outletId": "vulture",
  "outlet": "Vulture",
  "criticName": "Jesse Green",
  "url": null,
  "publishDate": null,
  "fullText": null,
  "isFullReview": false,
  "bwwExcerpt": "Take the score, by Stephen Flaherty and Lynn Ahrens, who (as Ragtimedemonstrated) know their way around iconic Americana. They work very carefully here, slowly developing a general musical atmosphere with shards of sung dialogue before allowing the emergence of a straight-up song. But, boy, do you f...",
  "bwwRoundupUrl": null,
  "bwwThumb": null,
  "showScoreExcerpt": null,
  "contentTier": "excerpt",
  "contentTierReason": "Only aggregator excerpts available",
  "source": "bww-roundup",
  "sources": [
    "bww-roundup"
  ]
}
