{
  "showId": "the-little-foxes-2017",
  "outletId": "wnyc",
  "outlet": "WNYC",
  "criticName": "Jennifer Vanasco",
  "url": "http://www.wnyc.org/story/review-little-foxes-has-sharp-teeth/",
  "publishDate": null,
  "fullText": null,
  "isFullReview": false,
  "dtliExcerpt": null,
  "originalScore": null,
  "assignedScore": null,
  "source": "show-score-playwright",
  "dtliThumb": null,
  "dtliUrl": null,
  "bwwExcerpt": null,
  "bwwRoundupUrl": null,
  "showScoreExcerpt": "\"Daniel Sullivan's production is thrilling. In a stroke of casting genius, Laura Linney and Cynthia Nixon alternate in the Regina and Birdie roles at different performances. You can see both — and you should...What struck me hardest is how rounded these characters are...The best part? Both women characters are too strong to be merely victims. This is a compelling play about power and its abuses...It's also a complex character study. This is one you shouldn't miss.\"\n\nRead more",
  "contentTier": "excerpt",
  "contentTierReason": "Only aggregator excerpts available"
}