{
  "showId": "a-dolls-house-2023",
  "outletId": "deadline",
  "outlet": "Deadline",
  "criticName": "Pete Hammond",
  "url": "https://deadline.com/2023/03/a-dolls-house-review-jessica-chastain-broadway-1235294837/",
  "publishDate": "March 10, 2023",
  "fullText": null,
  "isFullReview": false,
  "dtliExcerpt": "Chastain commands the stage with a performance that is both fierce and nuanced, bringing fresh energy to Ibsen's classic while honoring its timeless themes.",
  "originalScore": null,
  "assignedScore": null,
  "source": "web-search",
  "dtliThumb": null,
  "dtliUrl": null,
  "bwwExcerpt": null,
  "bwwRoundupUrl": null,
  "showScoreExcerpt": "Chastain commands the stage with a performance that is both fierce and nuanced, bringing fresh energy to Ibsen's classic while honoring its timeless themes.",
  "contentTier": "excerpt",
  "contentTierReason": "Only aggregator excerpts available"
}