{
  "showId": "oklahoma-2019",
  "outletId": "musical-theatre-review",
  "outlet": "Musical Theatre Review",
  "criticName": "Ron Cohen",
  "url": "http://musicaltheatrereview.com/oklahoma-circle-in-the-square-new-york/",
  "publishDate": null,
  "fullText": null,
  "isFullReview": false,
  "dtliExcerpt": null,
  "originalScore": null,
  "assignedScore": null,
  "source": "show-score-playwright",
  "dtliThumb": null,
  "dtliUrl": null,
  "bwwExcerpt": null,
  "bwwRoundupUrl": null,
  "showScoreExcerpt": "\"Fish has found and brought to the fore the dark, dark colours underlying R&H’s buoyant tale...The orchestrations and arrangements...have a country-western twang or pop flavouring, but they still delight...Along with the festivities, though, there’s a hint of violence...Splendid cast...The move to Broadway has maintained the show’s intimacy, while somehow enriching the musicality, and added even a bit more ingrained depth to its characters...Dynamic theatre.”\n\nRead more",
  "contentTier": "excerpt",
  "contentTierReason": "Only aggregator excerpts available"
}