{
  "showId": "fool-for-love-2015",
  "outletId": "usatoday",
  "outlet": "USA Today",
  "criticName": "Elysa Gardner",
  "url": "http://www.usatoday.com/story/life/theater/2015/10/08/fool-love-blazes-onto-broadway/73527156/",
  "publishDate": null,
  "fullText": null,
  "isFullReview": false,
  "bwwExcerpt": "And for 75 minutes, director Daniel Aukin and his flawless cast, led by a riveting Nina Arianda and a fiercely unsettling Sam Rockwell, deliver, never allowing themselves or the audience an uncharged moment...The arrival of a gentleman caller named Martin -- an awkward but patient fellow, imbued wit...",
  "bwwRoundupUrl": null,
  "bwwThumb": null,
  "showScoreExcerpt": null,
  "contentTier": "excerpt",
  "contentTierReason": "Only aggregator excerpts available",
  "source": "bww-roundup",
  "sources": [
    "bww-roundup",
    "playbill-verdict"
  ],
  "playbillVerdictUrl": "http://www.usatoday.com/story/life/theater/2015/10/08/fool-love-blazes-onto-broadway/73527156/",
  "duplicateOf": "usatoday--unknown.json"
}
