{
  "showId": "once-2012",
  "outletId": "theatrely",
  "outlet": "Theatrely",
  "criticName": "Joey Sims",
  "url": "https://www.theatrely.com/post/once-upon-a-mattress-joyfully-heads-back-to-broadway-review",
  "playbillVerdictUrl": "https://www.theatrely.com/post/once-upon-a-mattress-joyfully-heads-back-to-broadway-review",
  "source": "playbill-verdict",
  "sources": [
    "playbill-verdict"
  ],
  "wrongShow": true,
  "wrongShowNote": "PV scraper matched wrong article (actually Once Upon a Mattress (2024)). Flagged by cleanup script."
}
