{
  "showId": "the-great-gatsby-2024",
  "outletId": "nytg",
  "outlet": "New York Theatre Guide",
  "criticName": "Caroline Cao",
  "url": "https://www.newyorktheatreguide.com/reviews/the-great-gatsby-broadway-review-jeremy-jordan-eva-noblezada",
  "publishDate": "April 25, 2024",
  "dtliExcerpt": "Something about the production feels too spic and span by the time it ends: Missing is a mess left behind by the Roaring Twenties excess. I felt the warmth in The Great Gatsby, but it was begging to bring on the heat.",
  "fullText": null,
  "isFullReview": false,
  "originalScore": null,
  "assignedScore": null,
  "dtliThumb": "Meh",
  "source": "dtli",
  "showScoreExcerpt": null,
  "bwwExcerpt": null,
  "bwwThumb": null,
  "llmScore": null,
  "llmMetadata": null,
  "ensembleData": null
}