{
  "showId": "the-roommate-2024",
  "outletId": "THR",
  "outlet": "The Hollywood Reporter",
  "criticName": "Angie Han",
  "url": "https://www.hollywoodreporter.com/lifestyle/arts/the-roommate-broadway-review-mia-farrow-patti-lupone-1235994638/",
  "publishDate": "September 13, 2024",
  "fullText": "The play works best when it leans into the absurdity of its premise, letting Farrow and LuPone find the comedy in their characters' mutual bewilderment.",
  "isFullReview": false,
  "dtliExcerpt": "The play works best when it leans into the absurdity of its premise, letting Farrow and LuPone find the comedy in their characters' mutual bewilderment.",
  "originalScore": null,
  "assignedScore": null,
  "source": "web-search",
  "dtliThumb": null,
  "needsScoring": true
}