{
  "showId": "groundhog-day-2017",
  "outletId": "the-independent-uk",
  "outlet": "The Independent",
  "criticName": "Paul Taylor",
  "url": "http://www.independent.co.uk/arts-entertainment/theatre-dance/reviews/groundhog-day-old-vic-theatre-review-such-a-tonic-that-its-a-pity-you-cant-get-a-repeat-prescription-a7195351.html",
  "publishDate": null,
  "fullText": null,
  "isFullReview": false,
  "dtliExcerpt": null,
  "originalScore": null,
  "assignedScore": null,
  "source": "show-score-playwright",
  "dtliThumb": null,
  "dtliUrl": null,
  "bwwExcerpt": null,
  "bwwRoundupUrl": null,
  "showScoreExcerpt": "\"This hotly anticipated show turns out to be such a tonic that it's a pity you can't get a repeat prescription for it...Retunes our sense of the black hilarity and emotional depth of the central conceit...Matthew Warchus’s production is a miracle of stage-craft and technical coordination...Broadway star Andy Karl tackles the demanding central role with fantastic aplomb...It must be exhausting work but he makes the task of carrying the show look effortless.\"\n\nRead more",
  "contentTier": "excerpt",
  "contentTierReason": "Only aggregator excerpts available"
}